{
  "trips": [
    {
      "timestamp": 1585847951255,
      "parkCode": "grte",
      "campgroundId": "94",
      "foodId": 52,
      "attractionId": 51,
      "id": 1
    },
    {
      "timestamp": 1585850682005,
      "parkCode": "grte",
      "campgroundId": "95",
      "foodId": 52,
      "attractionId": 51,
      "id": 2
    },
    {
      "timestamp": 1585853271062,
      "parkCode": "grte",
      "campgroundId": "94",
      "foodId": 52,
      "attractionId": 51,
      "id": 3
    }
  ]
}